[
  {
    "id": "mediumStoryA-1",
    "parents": "mediumStoryA",
    "title": "David and Emma",
    "content": "David and Emma looked at each other across the table. The young couple were happy: the food was delicious, the light from the candles was soft and the music was perfect. David looked at Emma's beautiful smile. All the pain of his last break-up disappeared. All his doubts and fears about love had gone. His hand reached out and touched hers.'I want to ask you something.' David searched her eyes. Could she guess what was coming?",
    "filter": 1,
    "leaf": 1,
    "autosplit": 1
  },
  {
    "id": "mediumStoryA-2",
    "parents": "mediumStoryA",
    "title": "Waiting for a light",
    "content": "He watched the building. He was waiting for a light to come on to show him which flat was theirs. One minute passed … two … there it was! The light went on in a third-floor window. He saw Emma for a moment as she closed the curtains.",
    "filter": 1,
    "leaf": 1,
    "autosplit": 1
  }
]